tccpy/__init__.py
tccpy/main.py
tccpy-0.18.dist-info/LICENSE
tccpy-0.18.dist-info/METADATA
tccpy-0.18.dist-info/WHEEL
tccpy-0.18.dist-info/top_level.txt
tccpy-0.18.dist-info/RECORD
