Metadata-Version: 2.2
Name: tccpy
Version: 0.18
Summary: A Python implementation of the Target Confusability Competition (TCC) memory model
Home-page: https://github.com/ilabsweden/tccpy
License-File: LICENSE
Dynamic: home-page
Dynamic: summary
